{
  "meta": {
    "version": "1.0.0",
    "description": "Centralized pool configuration for Alphix V4 pools on Base Mainnet",
    "chainId": 8453,
    "chainName": "Base"
  },
  "contracts": {
    "poolManager": "0x498581ff718922c3f8e6a244956af099b2652b2b",
    "universalRouter": "0x6ff5693b99212da76ad316178a184ab56d299b43",
    "quoter": "0x0d5e0f971ed27fbff6c2837bf31316121532048d",
    "positionManager": "0x7c5f5a4bbd8fd63184577525326123b519429bdc",
    "stateView": "0xa3c0c9b65bad0b08107aa264b0f3db444b867a71"
  },
  "hooks": {
    "alphixHookId": "0xc025186214711638070aF4e27B57B3D4B10B7Fff"
  },
  "tokens": {
    "ETH": {
      "symbol": "ETH",
      "name": "Ethereum",
      "address": "0x0000000000000000000000000000000000000000",
      "decimals": 18,
      "icon": "/tokens/ETH.png"
    },
    "USDC": {
      "symbol": "USDC",
      "name": "USD Coin",
      "address": "0x833589fCD6eDb6E08f4c7C32D4f71b54bdA02913",
      "decimals": 6,
      "icon": "/tokens/USDC.png",
      "usdPrice": "1.0"
    },
    "USDT": {
      "symbol": "USDT",
      "name": "Tether USD",
      "address": "0xfde4C96c8593536E31F229EA8f37b2ADa2699bb2",
      "decimals": 6,
      "icon": "/tokens/USDT.png",
      "usdPrice": "1.0"
    }
  },
  "pools": [
    {
      "id": "usdc-usdt",
      "name": "USDC/USDT",
      "description": "Stablecoin pair with dynamic fees",
      "subgraphId": "0x7f9704e6f22b3aaf8315c7bceffb63c8a1b06de964020efe6be2cb27ea20e632",
      "currency0": {
        "symbol": "USDC",
        "address": "0x833589fCD6eDb6E08f4c7C32D4f71b54bdA02913"
      },
      "currency1": {
        "symbol": "USDT",
        "address": "0xfde4C96c8593536E31F229EA8f37b2ADa2699bb2"
      },
      "fee": 8388608,
      "tickSpacing": 1,
      "hooks": "0xc025186214711638070aF4e27B57B3D4B10B7Fff",
      "enabled": true,
      "featured": true,
      "type": "Stable",
      "rehypoRange": {
        "min": "1.001",
        "max": "1.001601",
        "isFullRange": false
      }
    },
    {
      "id": "eth-usdc",
      "name": "ETH/USDC",
      "description": "ETH/USDC pair with dynamic fees",
      "subgraphId": "0xa92784c3030d9c4743dfdbc4da540d3f0f9d2742a47b83304d6d2d5eee45fb3b",
      "currency0": {
        "symbol": "ETH",
        "address": "0x0000000000000000000000000000000000000000"
      },
      "currency1": {
        "symbol": "USDC",
        "address": "0x833589fCD6eDb6E08f4c7C32D4f71b54bdA02913"
      },
      "fee": 8388608,
      "tickSpacing": 10,
      "hooks": "0xc025186214711638070aF4e27B57B3D4B10B7Fff",
      "enabled": true,
      "featured": true,
      "type": "Volatile",
      "rehypoRange": {
        "min": "0",
        "max": "∞",
        "isFullRange": true
      }
    }
  ],
  "fees": {
    "initialFee": 8388608,
    "initialTargetRatio": "1000000000000000000",
    "currentRatio": "700000000000000000"
  },
  "_comments": {
    "note": "Base Mainnet configuration for Alphix V4 pools.",
    "subgraphId": "CRITICAL: The 'subgraphId' field contains the ACTUAL on-chain poolId (bytes32). DO NOT recalculate this value using keccak256 or any other method.",
    "fee": "The fee value 8388608 is the dynamic fee flag (0x800000). This indicates the pool uses dynamic fees managed by the hook contract."
  }
}
